{
  "id": "P0014",
  "name": "石勇",
  "english_name": "Shi Yong",
  "birthday": "1972-06-10",
  "position": "DF",
  "origin": "天津",
  "headshot": "images/players/default.jpg",
  "short_description": "待内容补充。",
  "career_summary": {
    "total_apps": 62,
    "total_goals": 0,
    "total_wins": 26,
    "total_clean_sheets": 18,
    "win_rate": 41.9,
    "clean_sheet_rate": 29.0,
    "goals_per_game": 0.0,
    "active_years": "1994 - 2002"
  },
  "yearly_stats": [
    {
      "year": 1994,
      "team": "天津",
      "apps": 3,
      "goals": 0,
      "wins": 2,
      "win_rate": 66.7,
      "clean_sheets": 2,
      "clean_sheet_rate": 66.7,
      "goals_per_game": 0.0,
      "competitions": [
        {
          "name": "甲B",
          "apps": 3,
          "goals": 0,
          "wins": 2,
          "win_rate": 66.7,
          "clean_sheets": 2,
          "clean_sheet_rate": 66.7,
          "goals_per_game": 0.0
        }
      ]
    },
    {
      "year": 1995,
      "team": "天津三星",
      "apps": 20,
      "goals": 0,
      "wins": 6,
      "win_rate": 30.0,
      "clean_sheets": 4,
      "clean_sheet_rate": 20.0,
      "goals_per_game": 0.0,
      "competitions": [
        {
          "name": "甲A",
          "apps": 18,
          "goals": 0,
          "wins": 6,
          "win_rate": 33.3,
          "clean_sheets": 4,
          "clean_sheet_rate": 22.2,
          "goals_per_game": 0.0
        },
        {
          "name": "足协杯",
          "apps": 2,
          "goals": 0,
          "wins": 0,
          "win_rate": 0.0,
          "clean_sheets": 0,
          "clean_sheet_rate": 0.0,
          "goals_per_game": 0.0
        }
      ]
    },
    {
      "year": 1996,
      "team": "天津三星",
      "apps": 13,
      "goals": 0,
      "wins": 6,
      "win_rate": 46.2,
      "clean_sheets": 4,
      "clean_sheet_rate": 30.8,
      "goals_per_game": 0.0,
      "competitions": [
        {
          "name": "甲A",
          "apps": 9,
          "goals": 0,
          "wins": 4,
          "win_rate": 44.4,
          "clean_sheets": 3,
          "clean_sheet_rate": 33.3,
          "goals_per_game": 0.0
        },
        {
          "name": "足协杯",
          "apps": 4,
          "goals": 0,
          "wins": 2,
          "win_rate": 50.0,
          "clean_sheets": 1,
          "clean_sheet_rate": 25.0,
          "goals_per_game": 0.0
        }
      ]
    },
    {
      "year": 1998,
      "team": "天津泰达",
      "apps": 15,
      "goals": 0,
      "wins": 8,
      "win_rate": 53.3,
      "clean_sheets": 5,
      "clean_sheet_rate": 33.3,
      "goals_per_game": 0.0,
      "competitions": [
        {
          "name": "甲B",
          "apps": 15,
          "goals": 0,
          "wins": 8,
          "win_rate": 53.3,
          "clean_sheets": 5,
          "clean_sheet_rate": 33.3,
          "goals_per_game": 0.0
        }
      ]
    },
    {
      "year": 2001,
      "team": "天津泰达",
      "apps": 7,
      "goals": 0,
      "wins": 3,
      "win_rate": 42.9,
      "clean_sheets": 3,
      "clean_sheet_rate": 42.9,
      "goals_per_game": 0.0,
      "competitions": [
        {
          "name": "甲A",
          "apps": 7,
          "goals": 0,
          "wins": 3,
          "win_rate": 42.9,
          "clean_sheets": 3,
          "clean_sheet_rate": 42.9,
          "goals_per_game": 0.0
        }
      ]
    },
    {
      "year": 2002,
      "team": "天津泰达",
      "apps": 4,
      "goals": 0,
      "wins": 1,
      "win_rate": 25.0,
      "clean_sheets": 0,
      "clean_sheet_rate": 0.0,
      "goals_per_game": 0.0,
      "competitions": [
        {
          "name": "甲A",
          "apps": 4,
          "goals": 0,
          "wins": 1,
          "win_rate": 25.0,
          "clean_sheets": 0,
          "clean_sheet_rate": 0.0,
          "goals_per_game": 0.0
        }
      ]
    }
  ],
  "identity": {
    "is_player": true,
    "is_coach": false,
    "dual_role_description": null
  },
  "honors": [],
  "related_photos": [],
  "coaching_record": null
}