{
  "id": "P0141",
  "name": "杨君",
  "english_name": "Yang Jun",
  "birthday": "1980-06-10",
  "position": "GK",
  "origin": "天津",
  "headshot": "images/players/default.jpg",
  "short_description": "待内容补充。",
  "career_summary": {
    "total_apps": 91,
    "total_goals": 0,
    "total_wins": 39,
    "total_clean_sheets": 35,
    "win_rate": 42.9,
    "clean_sheet_rate": 38.5,
    "goals_per_game": 0.0,
    "active_years": "2007 - 2009"
  },
  "yearly_stats": [
    {
      "year": 2007,
      "team": "天津泰达",
      "apps": 28,
      "goals": 0,
      "wins": 12,
      "win_rate": 42.9,
      "clean_sheets": 14,
      "clean_sheet_rate": 50.0,
      "goals_per_game": 0.0,
      "competitions": [
        {
          "name": "中超",
          "apps": 28,
          "goals": 0,
          "wins": 12,
          "win_rate": 42.9,
          "clean_sheets": 14,
          "clean_sheet_rate": 50.0,
          "goals_per_game": 0.0
        }
      ]
    },
    {
      "year": 2008,
      "team": "天津泰达",
      "apps": 29,
      "goals": 0,
      "wins": 15,
      "win_rate": 51.7,
      "clean_sheets": 9,
      "clean_sheet_rate": 31.0,
      "goals_per_game": 0.0,
      "competitions": [
        {
          "name": "中超",
          "apps": 29,
          "goals": 0,
          "wins": 15,
          "win_rate": 51.7,
          "clean_sheets": 9,
          "clean_sheet_rate": 31.0,
          "goals_per_game": 0.0
        }
      ]
    },
    {
      "year": 2009,
      "team": "天津泰达",
      "apps": 34,
      "goals": 0,
      "wins": 12,
      "win_rate": 35.3,
      "clean_sheets": 12,
      "clean_sheet_rate": 35.3,
      "goals_per_game": 0.0,
      "competitions": [
        {
          "name": "中超",
          "apps": 30,
          "goals": 0,
          "wins": 12,
          "win_rate": 40.0,
          "clean_sheets": 11,
          "clean_sheet_rate": 36.7,
          "goals_per_game": 0.0
        },
        {
          "name": "亚冠",
          "apps": 4,
          "goals": 0,
          "wins": 0,
          "win_rate": 0.0,
          "clean_sheets": 1,
          "clean_sheet_rate": 25.0,
          "goals_per_game": 0.0
        }
      ]
    }
  ],
  "identity": {
    "is_player": true,
    "is_coach": false,
    "dual_role_description": null
  },
  "honors": [],
  "related_photos": [],
  "coaching_record": null
}