{
  "id": "P0157",
  "name": "凯撒",
  "english_name": "Alin Nicolae Chita",
  "birthday": "1978-08-22",
  "position": "DF",
  "origin": "罗马尼亚",
  "headshot": "images/players/default.jpg",
  "short_description": "待内容补充。",
  "career_summary": {
    "total_apps": 7,
    "total_goals": 0,
    "total_wins": 3,
    "total_clean_sheets": 3,
    "win_rate": 42.9,
    "clean_sheet_rate": 42.9,
    "goals_per_game": 0.0,
    "active_years": "2009 - 2009"
  },
  "yearly_stats": [
    {
      "year": 2009,
      "team": "天津泰达",
      "apps": 7,
      "goals": 0,
      "wins": 3,
      "win_rate": 42.9,
      "clean_sheets": 3,
      "clean_sheet_rate": 42.9,
      "goals_per_game": 0.0,
      "competitions": [
        {
          "name": "中超",
          "apps": 7,
          "goals": 0,
          "wins": 3,
          "win_rate": 42.9,
          "clean_sheets": 3,
          "clean_sheet_rate": 42.9,
          "goals_per_game": 0.0
        }
      ]
    }
  ],
  "identity": {
    "is_player": true,
    "is_coach": false,
    "dual_role_description": null
  },
  "honors": [],
  "related_photos": [],
  "coaching_record": null
}