{
  "id": "P0322",
  "name": "张卫",
  "english_name": "Zhang Wei",
  "birthday": "1993-03-28",
  "position": "DF",
  "origin": "河南商丘",
  "headshot": "images/players/default.jpg",
  "short_description": "待内容补充。",
  "career_summary": {
    "total_apps": 8,
    "total_goals": 0,
    "total_wins": 4,
    "win_rate": 50.0,
    "active_years": "2022 - 2022",
    "goals_per_game": 0.0
  },
  "yearly_stats": [
    {
      "year": 2022,
      "team": "天津津门虎",
      "apps": 8,
      "goals": 0,
      "wins": 4,
      "win_rate": 50.0,
      "goals_per_game": 0.0
    }
  ],
  "identity": {
    "is_player": true,
    "is_coach": false,
    "dual_role_description": null
  },
  "honors": [],
  "related_photos": [],
  "coaching_record": null
}