{
  "id": "P0335",
  "name": "冷季轩",
  "english_name": "Leng Jixuan",
  "birthday": "2001-04-30",
  "position": "FW",
  "origin": "贵州六盘水",
  "headshot": "images/players/default.jpg",
  "short_description": "待内容补充。",
  "career_summary": {
    "total_apps": 4,
    "total_goals": 0,
    "total_wins": 1,
    "win_rate": 25.0,
    "active_years": "2023 - 2023",
    "goals_per_game": 0.0
  },
  "yearly_stats": [
    {
      "year": 2023,
      "team": "天津津门虎",
      "apps": 4,
      "goals": 0,
      "wins": 1,
      "win_rate": 25.0,
      "goals_per_game": 0.0
    }
  ],
  "identity": {
    "is_player": true,
    "is_coach": false,
    "dual_role_description": null
  },
  "honors": [],
  "related_photos": [],
  "coaching_record": null
}